CONTRIBUTING.md
MANIFEST.in
README.rst
setup.py
docs/HISTORY.txt
docs/LICENSE.GPL
docs/LICENSE.txt
eea/__init__.py
eea.zotero.egg-info/PKG-INFO
eea.zotero.egg-info/SOURCES.txt
eea.zotero.egg-info/dependency_links.txt
eea.zotero.egg-info/entry_points.txt
eea.zotero.egg-info/namespace_packages.txt
eea.zotero.egg-info/not-zip-safe
eea.zotero.egg-info/requires.txt
eea.zotero.egg-info/top_level.txt
eea/zotero/README.txt
eea/zotero/__init__.py
eea/zotero/configure.zcml
eea/zotero/interfaces.py
eea/zotero/permissions.zcml
eea/zotero/profiles.zcml
eea/zotero/setuphandlers.py
eea/zotero/version.txt
eea/zotero/browser/__init__.py
eea/zotero/browser/configure.zcml
eea/zotero/browser/controlpanel.py
eea/zotero/ftests/eea/00_install_addon.js
eea/zotero/ftests/kgs/00_install_addon.js
eea/zotero/ftests/plone4/00_install_addon.js
eea/zotero/ftests/plone5/00_install_addon.js
eea/zotero/locales/__init__.py
eea/zotero/locales/eea.pot
eea/zotero/locales/plone-manual.pot
eea/zotero/locales/update.sh
eea/zotero/locales/bg/LC_MESSAGES/eea.po
eea/zotero/locales/bg/LC_MESSAGES/plone.po
eea/zotero/locales/cs/LC_MESSAGES/eea.po
eea/zotero/locales/cs/LC_MESSAGES/plone.po
eea/zotero/locales/da/LC_MESSAGES/eea.po
eea/zotero/locales/da/LC_MESSAGES/plone.po
eea/zotero/locales/de/LC_MESSAGES/eea.po
eea/zotero/locales/de/LC_MESSAGES/plone.po
eea/zotero/locales/el/LC_MESSAGES/eea.po
eea/zotero/locales/el/LC_MESSAGES/plone.po
eea/zotero/locales/en/LC_MESSAGES/eea.po
eea/zotero/locales/en/LC_MESSAGES/plone.po
eea/zotero/locales/es/LC_MESSAGES/eea.po
eea/zotero/locales/es/LC_MESSAGES/plone.po
eea/zotero/locales/et/LC_MESSAGES/eea.po
eea/zotero/locales/et/LC_MESSAGES/plone.po
eea/zotero/locales/eu/LC_MESSAGES/eea.po
eea/zotero/locales/eu/LC_MESSAGES/plone.po
eea/zotero/locales/fi/LC_MESSAGES/eea.po
eea/zotero/locales/fi/LC_MESSAGES/plone.po
eea/zotero/locales/fr/LC_MESSAGES/eea.po
eea/zotero/locales/fr/LC_MESSAGES/plone.po
eea/zotero/locales/hr/LC_MESSAGES/eea.po
eea/zotero/locales/hr/LC_MESSAGES/plone.po
eea/zotero/locales/hu/LC_MESSAGES/eea.po
eea/zotero/locales/hu/LC_MESSAGES/plone.po
eea/zotero/locales/is/LC_MESSAGES/eea.po
eea/zotero/locales/is/LC_MESSAGES/plone.po
eea/zotero/locales/it/LC_MESSAGES/eea.po
eea/zotero/locales/it/LC_MESSAGES/plone.po
